linkup_monitor/__init__.py
linkup_monitor/add_types.py
linkup_monitor/monitor.py
linkup_monitor/postgres_client.py
linkup_monitor-1.0.0.dist-info/licenses/LICENSE
linkup_monitor-1.0.0.dist-info/METADATA
linkup_monitor-1.0.0.dist-info/WHEEL
linkup_monitor-1.0.0.dist-info/top_level.txt
linkup_monitor-1.0.0.dist-info/RECORD
