Metadata-Version: 2.4
Name: linkup-monitor
Version: 1.0.0
Summary: linkup-monitor: a monitoring solution for world's best search for AI apps
Author-email: "Clelia (Astra) Bertelli" <astraberte9@gmail.com>
Project-URL: Homepage, https://github.com/AstraBert/linkup-monitor
Project-URL: Issues, https://github.com/AstraBert/linkup-monitor/issues
Classifier: Programming Language :: Python :: 3
Classifier: License :: OSI Approved :: MIT License
Classifier: Operating System :: OS Independent
Requires-Python: >=3.11
License-File: LICENSE
Requires-Dist: pydantic
Requires-Dist: sqlalchemy
Requires-Dist: psycopg2-binary
Requires-Dist: pandas
Requires-Dist: linkup-sdk
Dynamic: license-file
